<Device>
  <DeviceInformation DeviceName="ANKLE_R" SerialNumber="003CD993" FirmwareVersion="v1.15 (Apr 26 2021 10:29:52)" BootloaderVersion="v2.0 (Mar 27 2019 15:56:10)" HardwareVersion="v1.6 (June 2021)" />
  <ConnectionInformation ConnectionType="Udp" SendIPAddress="192.168.0.102" SendPort="9000" AdapterIPAddress="192.168.0.100" ReceivePort="8102" AdapterName="Intel(R) Wi-Fi 6 AX200 160MHz" />
  <TimeStamps First="2021-09-22 11:33:15.009" Last="2021-09-22 11:35:05.343" TimeSpan="00:01:50.334" />
  <FilesCreated>
    <File Name="sensors.csv" Messages="3297" />
    <File Name="quaternion.csv" Messages="3297" />
    <File Name="temperature.csv" Messages="110" />
    <File Name="humidity.csv" Messages="110" />
    <File Name="battery.csv" Messages="110" />
    <File Name="rssi.csv" Messages="220" />
  </FilesCreated>
  <Statistics BytesReceived="39482704" PacketsReceived="229115" BundlesReceived="724054" MessagesReceived="495022" ReceiveErrors="0" />
</Device>