{"videoId":244567419,"videoName":"Actor_4_Bed.mp4","createdAt":"2022-04-30T17:24:18.986Z","updatedAt":"2022-04-30T17:24:18.986Z","description":"","tags":[{"name":"actor_repositioning","id":124066892,"tagId":30231303,"frameRange":[0,125],"labelerLogin":"yami","createdAt":"2022-04-30T17:25:14.268Z","updatedAt":"2022-04-30T17:25:14.268Z"},{"name":"lie_still","id":124066893,"tagId":30231492,"frameRange":[0,125],"labelerLogin":"yami","createdAt":"2022-04-30T17:25:20.879Z","updatedAt":"2022-04-30T17:25:20.879Z"},{"name":"sit_up_from_lying","id":124066894,"tagId":30231304,"frameRange":[126,224],"labelerLogin":"yami","createdAt":"2022-04-30T17:25:37.463Z","updatedAt":"2022-04-30T17:25:37.463Z"},{"name":"stand_up_from_sit","id":124066895,"tagId":30231316,"frameRange":[225,285],"labelerLogin":"yami","createdAt":"2022-04-30T17:26:22.241Z","updatedAt":"2022-04-30T17:26:22.241Z"},{"name":"stand_still","id":124066896,"tagId":30231305,"frameRange":[286,314],"labelerLogin":"yami","createdAt":"2022-04-30T17:26:46.138Z","updatedAt":"2022-04-30T17:26:46.138Z"},{"name":"sit_down_from_standing","id":124066897,"tagId":30231307,"frameRange":[315,349],"labelerLogin":"yami","createdAt":"2022-04-30T17:27:07.258Z","updatedAt":"2022-04-30T17:27:07.258Z"},{"name":"lie_down_from_sitting","id":124066898,"tagId":30231306,"frameRange":[350,462],"labelerLogin":"yami","createdAt":"2022-04-30T17:27:21.189Z","updatedAt":"2022-04-30T17:27:21.189Z"},{"name":"lie_still","id":124066899,"tagId":30231492,"frameRange":[463,516],"labelerLogin":"yami","createdAt":"2022-04-30T17:27:50.899Z","updatedAt":"2022-04-30T17:27:50.899Z"},{"name":"actor_repositioning","id":124066900,"tagId":30231303,"frameRange":[315,516],"labelerLogin":"yami","createdAt":"2022-04-30T17:28:19.091Z","updatedAt":"2022-04-30T17:28:19.091Z"},{"name":"sit_up_from_lying","id":124066901,"tagId":30231304,"frameRange":[517,620],"labelerLogin":"yami","createdAt":"2022-04-30T17:28:45.708Z","updatedAt":"2022-04-30T17:28:45.708Z"},{"name":"stand_up_from_sit","id":124066902,"tagId":30231316,"frameRange":[621,667],"labelerLogin":"yami","createdAt":"2022-04-30T17:29:04.692Z","updatedAt":"2022-04-30T17:29:04.692Z"},{"name":"fall_frontal","id":124066903,"tagId":30231317,"frameRange":[668,716],"labelerLogin":"yami","createdAt":"2022-04-30T17:29:34.595Z","updatedAt":"2022-04-30T17:29:34.595Z"},{"name":"stand_up_from_floor","id":124066904,"tagId":30231310,"frameRange":[717,901],"labelerLogin":"yami","createdAt":"2022-04-30T17:29:54.028Z","updatedAt":"2022-04-30T17:29:54.028Z"},{"name":"sit_down_from_standing","id":124066905,"tagId":30231307,"frameRange":[902,958],"labelerLogin":"yami","createdAt":"2022-04-30T17:30:13.258Z","updatedAt":"2022-04-30T17:30:13.258Z"},{"name":"lie_down_from_sitting","id":124066906,"tagId":30231306,"frameRange":[959,1053],"labelerLogin":"yami","createdAt":"2022-04-30T17:31:45.155Z","updatedAt":"2022-04-30T17:31:45.155Z"},{"name":"lie_still","id":124066907,"tagId":30231492,"frameRange":[1054,1106],"labelerLogin":"yami","createdAt":"2022-04-30T17:32:10.937Z","updatedAt":"2022-04-30T17:32:10.937Z"},{"name":"actor_repositioning","id":124066909,"tagId":30231303,"frameRange":[717,1106],"labelerLogin":"yami","createdAt":"2022-04-30T17:32:45.048Z","updatedAt":"2022-04-30T17:32:45.048Z"},{"name":"sit_up_from_lying","id":124066910,"tagId":30231304,"frameRange":[1107,1209],"labelerLogin":"yami","createdAt":"2022-04-30T17:33:12.910Z","updatedAt":"2022-04-30T17:33:12.910Z"},{"name":"stand_up_from_sit","id":124066911,"tagId":30231316,"frameRange":[1210,1251],"labelerLogin":"yami","createdAt":"2022-04-30T17:33:44.173Z","updatedAt":"2022-04-30T17:33:44.173Z"},{"name":"fall_lateral","id":124066912,"tagId":30231308,"frameRange":[1252,1299],"labelerLogin":"yami","createdAt":"2022-04-30T17:34:12.549Z","updatedAt":"2022-04-30T17:34:12.549Z"},{"name":"stand_up_from_floor","id":124066913,"tagId":30231310,"frameRange":[1300,1441],"labelerLogin":"yami","createdAt":"2022-04-30T17:34:31.054Z","updatedAt":"2022-04-30T17:34:31.054Z"},{"name":"sit_down_from_standing","id":124066914,"tagId":30231307,"frameRange":[1442,1513],"labelerLogin":"yami","createdAt":"2022-04-30T17:34:52.542Z","updatedAt":"2022-04-30T17:34:52.542Z"},{"name":"lie_down_from_sitting","id":124066915,"tagId":30231306,"frameRange":[1514,1610],"labelerLogin":"yami","createdAt":"2022-04-30T17:35:21.644Z","updatedAt":"2022-04-30T17:35:21.644Z"},{"name":"lie_still","id":124066916,"tagId":30231492,"frameRange":[1611,1651],"labelerLogin":"yami","createdAt":"2022-04-30T17:35:51.612Z","updatedAt":"2022-04-30T17:35:51.612Z"},{"name":"actor_repositioning","id":124066917,"tagId":30231303,"frameRange":[1300,1651],"labelerLogin":"yami","createdAt":"2022-04-30T17:36:01.465Z","updatedAt":"2022-04-30T17:36:01.465Z"},{"name":"sit_up_from_lying","id":124066918,"tagId":30231304,"frameRange":[1652,1755],"labelerLogin":"yami","createdAt":"2022-04-30T17:36:22.972Z","updatedAt":"2022-04-30T17:36:22.972Z"},{"name":"stand_up_from_sit","id":124066919,"tagId":30231316,"frameRange":[1756,1789],"labelerLogin":"yami","createdAt":"2022-04-30T17:36:46.274Z","updatedAt":"2022-04-30T17:36:46.274Z"},{"name":"fall_lateral","id":124066920,"tagId":30231308,"frameRange":[1790,1838],"labelerLogin":"yami","createdAt":"2022-04-30T17:37:02.428Z","updatedAt":"2022-04-30T17:37:02.428Z"},{"name":"lie_down_on_the_floor","id":124066921,"tagId":30231309,"frameRange":[1839,1867],"labelerLogin":"yami","createdAt":"2022-04-30T17:37:29.440Z","updatedAt":"2022-04-30T17:37:29.440Z"},{"name":"stand_up_from_floor","id":124066922,"tagId":30231310,"frameRange":[1868,2008],"labelerLogin":"yami","createdAt":"2022-04-30T17:37:58.036Z","updatedAt":"2022-04-30T17:37:58.036Z"},{"name":"sit_down_from_standing","id":124066923,"tagId":30231307,"frameRange":[2009,2094],"labelerLogin":"yami","createdAt":"2022-04-30T17:38:56.035Z","updatedAt":"2022-04-30T17:38:56.035Z"},{"name":"lie_down_from_sitting","id":124066924,"tagId":30231306,"frameRange":[2095,2186],"labelerLogin":"yami","createdAt":"2022-04-30T17:39:25.234Z","updatedAt":"2022-04-30T17:39:25.234Z"},{"name":"lie_still","id":124066925,"tagId":30231492,"frameRange":[2187,2229],"labelerLogin":"yami","createdAt":"2022-04-30T17:40:10.631Z","updatedAt":"2022-04-30T17:40:10.631Z"},{"name":"actor_repositioning","id":124066926,"tagId":30231303,"frameRange":[1868,2229],"labelerLogin":"yami","createdAt":"2022-04-30T17:40:26.178Z","updatedAt":"2022-04-30T17:40:26.178Z"},{"name":"sit_up_from_lying","id":124066927,"tagId":30231304,"frameRange":[2230,2340],"labelerLogin":"yami","createdAt":"2022-04-30T17:40:50.712Z","updatedAt":"2022-04-30T17:40:50.712Z"},{"name":"stand_up_from_sit","id":124066928,"tagId":30231316,"frameRange":[2341,2377],"labelerLogin":"yami","createdAt":"2022-04-30T17:41:07.452Z","updatedAt":"2022-04-30T17:41:07.452Z"},{"name":"fall_crouch","id":124066929,"tagId":30231311,"frameRange":[2378,2423],"labelerLogin":"yami","createdAt":"2022-04-30T17:41:25.399Z","updatedAt":"2022-04-30T17:41:25.399Z"},{"name":"crouched_still","id":124066930,"tagId":30231312,"frameRange":[2424,2483],"labelerLogin":"yami","createdAt":"2022-04-30T17:41:58.589Z","updatedAt":"2022-04-30T17:41:58.589Z"},{"name":"stand_up_from_floor","id":124066931,"tagId":30231310,"frameRange":[2484,2595],"labelerLogin":"yami","createdAt":"2022-04-30T17:42:17.780Z","updatedAt":"2022-04-30T17:42:17.780Z"},{"name":"stand_still","id":124066932,"tagId":30231305,"frameRange":[2596,2721],"labelerLogin":"yami","createdAt":"2022-04-30T17:42:54.073Z","updatedAt":"2022-04-30T17:42:54.073Z"},{"name":"sit_down_from_standing","id":124066933,"tagId":30231307,"frameRange":[2722,2750],"labelerLogin":"yami","createdAt":"2022-04-30T17:43:06.351Z","updatedAt":"2022-04-30T17:43:06.351Z"},{"name":"lie_down_from_sitting","id":124066934,"tagId":30231306,"frameRange":[2751,2759],"labelerLogin":"yami","createdAt":"2022-04-30T17:43:37.325Z","updatedAt":"2022-04-30T17:43:37.325Z"},{"name":"actor_repositioning","id":124066935,"tagId":30231303,"frameRange":[2484,2759],"labelerLogin":"yami","createdAt":"2022-04-30T17:44:00.246Z","updatedAt":"2022-04-30T17:44:00.246Z"}],"objects":[],"size":{"height":1080,"width":1920},"framesCount":2760,"frames":[]}