{"videoId":245950361,"videoName":"Actor_4_Walk_Full_PH_Obj.mp4","createdAt":"2022-05-12T17:52:07.342Z","updatedAt":"2022-05-12T17:52:07.342Z","description":"","tags":[{"name":"stand_up_from_sit","id":124570768,"tagId":30231316,"frameRange":[258,314],"labelerLogin":"yami","createdAt":"2022-05-12T17:54:42.926Z","updatedAt":"2022-05-12T17:54:42.926Z"},{"name":"stand_up_from_sit","id":124570774,"tagId":30231316,"frameRange":[718,779],"labelerLogin":"yami","createdAt":"2022-05-12T17:57:07.253Z","updatedAt":"2022-05-12T17:57:07.253Z"},{"name":"pick_up_object","id":124570770,"tagId":30231319,"frameRange":[386,475],"labelerLogin":"yami","createdAt":"2022-05-12T17:56:09.157Z","updatedAt":"2022-05-12T17:56:09.157Z"},{"name":"walking","id":124570764,"tagId":30231318,"frameRange":[0,148],"labelerLogin":"yami","createdAt":"2022-05-12T17:52:49.627Z","updatedAt":"2022-05-12T17:52:49.627Z"},{"name":"sit_down_from_standing","id":124570765,"tagId":30231307,"frameRange":[149,175],"labelerLogin":"yami","createdAt":"2022-05-12T17:53:02.198Z","updatedAt":"2022-05-12T17:53:02.198Z"},{"name":"sit_still","id":124570766,"tagId":30231315,"frameRange":[176,257],"labelerLogin":"yami","createdAt":"2022-05-12T17:53:17.721Z","updatedAt":"2022-05-12T17:53:17.721Z"},{"name":"actor_repositioning","id":124570767,"tagId":30231303,"frameRange":[0,257],"labelerLogin":"yami","createdAt":"2022-05-12T17:54:26.645Z","updatedAt":"2022-05-12T17:54:26.645Z"},{"name":"walking","id":124570769,"tagId":30231318,"frameRange":[315,385],"labelerLogin":"yami","createdAt":"2022-05-12T17:55:16.529Z","updatedAt":"2022-05-12T17:55:16.529Z"},{"name":"walking","id":124570771,"tagId":30231318,"frameRange":[476,576],"labelerLogin":"yami","createdAt":"2022-05-12T17:56:22.762Z","updatedAt":"2022-05-12T17:56:22.762Z"},{"name":"sit_down_from_standing","id":124570772,"tagId":30231307,"frameRange":[577,628],"labelerLogin":"yami","createdAt":"2022-05-12T17:56:33.460Z","updatedAt":"2022-05-12T17:56:33.460Z"},{"name":"sit_still","id":124570773,"tagId":30231315,"frameRange":[629,717],"labelerLogin":"yami","createdAt":"2022-05-12T17:56:52.160Z","updatedAt":"2022-05-12T17:56:52.160Z"},{"name":"actor_repositioning","id":124570775,"tagId":30231303,"frameRange":[476,779],"labelerLogin":"yami","createdAt":"2022-05-12T17:57:17.014Z","updatedAt":"2022-05-12T17:57:17.014Z"}],"objects":[],"size":{"height":1080,"width":1920},"framesCount":780,"frames":[]}